mcpcn_video_to_gif/__init__.py
mcpcn_video_to_gif/server.py
mcpcn_video_to_gif-0.1.5.dist-info/METADATA
mcpcn_video_to_gif-0.1.5.dist-info/WHEEL
mcpcn_video_to_gif-0.1.5.dist-info/entry_points.txt
mcpcn_video_to_gif-0.1.5.dist-info/RECORD
